cuptlib_config/__init__.py
cuptlib_config/basic_config/__init__.py
cuptlib_config/basic_config/config_reader.py
cuptlib_config/basic_config/configclasses.py
cuptlib_config/palxfel/__init__.py
cuptlib_config/palxfel/config_io.py
cuptlib_config/palxfel/enums.py
cuptlib_config/palxfel/setting.py
cuptlib_config-0.1.6.dist-info/METADATA
cuptlib_config-0.1.6.dist-info/WHEEL
cuptlib_config-0.1.6.dist-info/top_level.txt
cuptlib_config-0.1.6.dist-info/RECORD
