Metadata-Version: 2.1
Name: cuptlib-config
Version: 0.1.6
Summary: configuration tools for XFEL
Home-page: https://github.com/SJB7777/cupdlib-config
Author: Isaac Yong
Author-email: esakyong1866@naver.com
Classifier: Development Status :: 1 - Planning
Classifier: Intended Audience :: Developers
Classifier: Programming Language :: Python :: 3
Classifier: Operating System :: Unix
Classifier: Operating System :: MacOS :: MacOS X
Classifier: Operating System :: Microsoft :: Windows
Requires-Python: >=3.8
